breath_ml/__init__.py
breath_ml/service.py
breath_ml-0.0.1.dist-info/LICENSE
breath_ml-0.0.1.dist-info/METADATA
breath_ml-0.0.1.dist-info/WHEEL
breath_ml-0.0.1.dist-info/top_level.txt
breath_ml-0.0.1.dist-info/RECORD
